health_check/__init__.py
health_check/__main__.py
health_check/apps.py
health_check/commands.py
health_check/settings.py
health_check/urls.py
health_check/utils.py
health_check/api/__init__.py
health_check/api/mixins.py
health_check/api/urls.py
health_check/api/views.py
health_check/management/__init__.py
health_check/management/commands/__init__.py
health_check/management/commands/health_check.py
health_check/management/commands/status.py
health_check/providers/__init__.py
health_check/providers/base.py
health_check/providers/health.py
health_check/providers/stats.py
health_check/providers/celery/__init__.py
health_check/providers/celery/health.py
health_check/providers/celery/stats.py
health_check/providers/django/__init__.py
health_check/providers/django/health.py
health_check/providers/django/stats.py
health_check/static/health_check/apps/health.js
health_check/static/health_check/apps/main.js
health_check/static/health_check/apps/stats.js
health_check/static/health_check/css/style.css
health_check/static/health_check/fonts/FontAwesome.otf
health_check/static/health_check/fonts/fontawesome-webfont.eot
health_check/static/health_check/fonts/fontawesome-webfont.svg
health_check/static/health_check/fonts/fontawesome-webfont.ttf
health_check/static/health_check/fonts/fontawesome-webfont.woff
health_check/static/health_check/fonts/fontawesome-webfont.woff2
health_check/templates/health_check/base.html
health_check/templates/health_check/health.html
health_check/templates/health_check/main.html
health_check/templates/health_check/stats.html
health_check-3.4.1.dist-info/DESCRIPTION.rst
health_check-3.4.1.dist-info/LICENSE.txt
health_check-3.4.1.dist-info/METADATA
health_check-3.4.1.dist-info/RECORD
health_check-3.4.1.dist-info/WHEEL
health_check-3.4.1.dist-info/entry_points.txt
health_check-3.4.1.dist-info/metadata.json
health_check-3.4.1.dist-info/top_level.txt
