Metadata-Version: 2.0
Name: health-check
Version: 3.4.1
Summary: Health Check is an application that provides an API to check the health health_check of some parts and some utilities like ping requests. This application can works as standalone or included in a Django project.
Home-page: https://github.com/PeRDy/health-check
Author: José Antonio Perdiguero López
Author-email: perdy.hh@gmail.com
License: GPLv3
Download-URL: https://github.com/PeRDy/health-check
Keywords: python django database cache celery health check
Platform: UNKNOWN
Classifier: Development Status :: 5 - Production/Stable
Classifier: Framework :: Django
Classifier: Intended Audience :: Developers
Classifier: License :: OSI Approved :: GNU General Public License v3 (GPLv3)
Classifier: Natural Language :: English
Classifier: Programming Language :: Python
Classifier: Programming Language :: Python :: 2
Classifier: Programming Language :: Python :: 3
Classifier: Topic :: Software Development :: Libraries :: Python Modules
Requires-Dist: GitPython (>=1.0)
Requires-Dist: pyyaml (>=3.12)
Requires-Dist: clinner (>=1.2)
Provides-Extra: dev
Requires-Dist: setuptools; extra == 'dev'
Requires-Dist: pip; extra == 'dev'
Requires-Dist: wheel; extra == 'dev'
Requires-Dist: twine; extra == 'dev'
Requires-Dist: bumpversion; extra == 'dev'
Requires-Dist: pre-commit; extra == 'dev'
Requires-Dist: GitPython (>=1.0); extra == 'dev'
Requires-Dist: pyyaml (>=3.12); extra == 'dev'
Requires-Dist: clinner (>=1.2); extra == 'dev'
Requires-Dist: coverage; extra == 'dev'
Requires-Dist: pytest; extra == 'dev'
Requires-Dist: pytest-cov; extra == 'dev'
Requires-Dist: prospector; extra == 'dev'
Requires-Dist: tox; extra == 'dev'
Requires-Dist: sphinx; extra == 'dev'
Requires-Dist: sphinx-rtd-theme; extra == 'dev'
